shapedata/__init__.py
shapedata/base_data_processing.py
shapedata/io.py
shapedata/utils.py
shapedata/single_shape/__init__.py
shapedata/single_shape/data_processing.py
shapedata/single_shape/dataset.py
tests/__init__.py
tests/test_io.py
tests/single_shape/__init__.py
tests/single_shape/test_data_processing.py
tests/single_shape/test_dataset.py
tests/single_shape/test_single_shape_2d.py
shapedata-0.2.0.dist-info/LICENSE
shapedata-0.2.0.dist-info/METADATA
shapedata-0.2.0.dist-info/WHEEL
shapedata-0.2.0.dist-info/top_level.txt
shapedata-0.2.0.dist-info/RECORD
