Metadata-Version: 2.1
Name: shapedata
Version: 0.2.0
Summary: UNKNOWN
Home-page: https://github.com/justussschock/shapedata
Author: Justus Schock
Author-email: justus.schock@rwth-aachen.de
License: BSD 2-Clause License
Requires-Dist: delira (>=0.4.1)
